apier/__init__.py
apier/cli/__init__.py
apier/cli/cli.py
apier/core/__init__.py
apier/core/api/__init__.py
apier/core/api/endpoints.py
apier/core/api/merge.py
apier/core/api/openapi.py
apier/core/api/tree.py
apier/core/build.py
apier/core/consts.py
apier/core/renderer.py
apier/extensions/__init__.py
apier/extensions/extensions.py
apier/extensions/input_parameters.py
apier/extensions/method_name.py
apier/extensions/pagination.py
apier/templates/__init__.py
apier/templates/python_tree/__init__.py
apier/templates/python_tree/base/__init__.py
apier/templates/python_tree/base/internal/__init__.py
apier/templates/python_tree/base/internal/content_disposition.py
apier/templates/python_tree/base/internal/content_type.py
apier/templates/python_tree/base/internal/expressions/__init__.py
apier/templates/python_tree/base/internal/expressions/evaluation.py
apier/templates/python_tree/base/internal/expressions/runtime.py
apier/templates/python_tree/base/internal/resource.py
apier/templates/python_tree/base/models/__init__.py
apier/templates/python_tree/base/models/basemodel.py
apier/templates/python_tree/base/models/exceptions.py
apier/templates/python_tree/base/models/extensions/__init__.py
apier/templates/python_tree/base/models/extensions/pagination.py
apier/templates/python_tree/base/models/pagination.py
apier/templates/python_tree/base/models/primitives.py
apier/templates/python_tree/base/requirements.txt
apier/templates/python_tree/functions.py
apier/templates/python_tree/model_generation/__init__.py
apier/templates/python_tree/model_generation/formatter.py
apier/templates/python_tree/model_generation/generate.py
apier/templates/python_tree/renderer.py
apier/templates/python_tree/ruff.toml
apier/templates/python_tree/security.py
apier/templates/python_tree/templates/api.jinja
apier/templates/python_tree/templates/api_operations.jinja
apier/templates/python_tree/templates/method_docstring.jinja
apier/templates/python_tree/templates/node.jinja
apier-0.6.0.dist-info/LICENSE
apier-0.6.0.dist-info/METADATA
apier-0.6.0.dist-info/WHEEL
apier-0.6.0.dist-info/entry_points.txt
apier-0.6.0.dist-info/RECORD
