Metadata-Version: 2.1
Name: apier
Version: 0.6.0
Summary: Turn API specs into code
Home-page: https://github.com/flusflas/apier
License: MIT
Keywords: openapi,code generation,api,specification,cli,swagger
Author: flusflas
Author-email: aflusflas@gmail.com
Requires-Python: >=3.9,<4.0
Classifier: Development Status :: 4 - Beta
Classifier: License :: OSI Approved :: MIT License
Classifier: Operating System :: OS Independent
Classifier: Programming Language :: Python
Classifier: Programming Language :: Python :: 3
Classifier: Programming Language :: Python :: 3.9
Classifier: Programming Language :: Python :: 3.10
Classifier: Programming Language :: Python :: 3.11
Classifier: Programming Language :: Python :: 3.12
Classifier: Programming Language :: Python :: 3.13
Classifier: Programming Language :: Python :: 3 :: Only
Classifier: Topic :: Utilities
Requires-Dist: Jinja2 (>=3.1.2,<4.0.0)
Requires-Dist: astor (>=0.8.1,<0.9.0)
Requires-Dist: black (>=25.1.0,<26.0.0)
Requires-Dist: click (>=8.1.7,<9.0.0)
Requires-Dist: datamodel-code-generator (>=0.31.2,<0.32.0)
Requires-Dist: flake8 (>=7.3.0,<8.0.0)
Requires-Dist: onedict (>=0.1.0,<0.2.0)
Requires-Dist: openapi-spec-validator (>=0.7.1,<0.8.0)
Requires-Dist: openapi3 (>=1.7.0,<2.0.0)
Requires-Dist: prance (>=23.6.21.0,<24.0.0.0)
Requires-Dist: pydantic (>=1.10.18,<2.0.0)
Requires-Dist: requests-toolbelt (>=1.0.0,<2.0.0)
Requires-Dist: ruff (>=0.6.2,<0.7.0)
Requires-Dist: vulture (>=2.11,<3.0)
Requires-Dist: xmltodict (>=0.13.0,<0.14.0)
Project-URL: Repository, https://github.com/flusflas/apier
